aiofranka/__init__.py
aiofranka/client.py
aiofranka/controller.py
aiofranka/robot.py
aiofranka/model/CHANGELOG.md
aiofranka/model/LICENSE
aiofranka/model/README.md
aiofranka/model/fr3.png
aiofranka/model/fr3.xml
aiofranka/model/scene.xml
aiofranka/model/assets/link0.obj
aiofranka/model/assets/link0.stl
aiofranka/model/assets/link0_0.obj
aiofranka/model/assets/link0_1.obj
aiofranka/model/assets/link0_2.obj
aiofranka/model/assets/link0_3.obj
aiofranka/model/assets/link0_4.obj
aiofranka/model/assets/link0_5.obj
aiofranka/model/assets/link0_6.obj
aiofranka/model/assets/link1.obj
aiofranka/model/assets/link1.stl
aiofranka/model/assets/link2.obj
aiofranka/model/assets/link2.stl
aiofranka/model/assets/link3.obj
aiofranka/model/assets/link3.stl
aiofranka/model/assets/link3_0.obj
aiofranka/model/assets/link3_1.obj
aiofranka/model/assets/link4.obj
aiofranka/model/assets/link4.stl
aiofranka/model/assets/link4_0.obj
aiofranka/model/assets/link4_1.obj
aiofranka/model/assets/link5.obj
aiofranka/model/assets/link5.stl
aiofranka/model/assets/link5_0.obj
aiofranka/model/assets/link5_1.obj
aiofranka/model/assets/link5_2.obj
aiofranka/model/assets/link6.obj
aiofranka/model/assets/link6.stl
aiofranka/model/assets/link6_0.obj
aiofranka/model/assets/link6_1.obj
aiofranka/model/assets/link6_2.obj
aiofranka/model/assets/link6_3.obj
aiofranka/model/assets/link6_4.obj
aiofranka/model/assets/link6_5.obj
aiofranka/model/assets/link6_6.obj
aiofranka/model/assets/link6_7.obj
aiofranka/model/assets/link7.obj
aiofranka/model/assets/link7.stl
aiofranka/model/assets/link7_0.obj
aiofranka/model/assets/link7_1.obj
aiofranka/model/assets/link7_2.obj
aiofranka/model/assets/link7_3.obj
aiofranka/utils/__init__.py
aiofranka/utils/camera_stream.py
aiofranka/utils/inject.js
aiofranka-0.2.0.dist-info/METADATA
aiofranka-0.2.0.dist-info/WHEEL
aiofranka-0.2.0.dist-info/top_level.txt
aiofranka-0.2.0.dist-info/RECORD
