Metadata-Version: 2.4
Name: aiofranka
Version: 0.2.0
Summary: A Python package for Franka robot control using asyncio.
Home-page: https://github.com/Improbable-AI/bifranka
Author: MIT Improbable AI Lab
Author-email: 
License: MIT
Project-URL: Homepage, https://github.com/Improbable-AI/aiofranka
Project-URL: Repository, https://github.com/Improbable-AI/aiofranka
Classifier: Programming Language :: Python :: 3
Classifier: Programming Language :: Python :: 3.8
Classifier: Programming Language :: Python :: 3.9
Classifier: Programming Language :: Python :: 3.10
Classifier: Programming Language :: Python :: 3.11
Classifier: License :: OSI Approved :: MIT License
Classifier: Operating System :: OS Independent
Requires-Python: >3.7
Requires-Dist: pylibfranka
Requires-Dist: ruckig
Requires-Dist: numpy
Requires-Dist: scipy
Requires-Dist: mujoco
Requires-Dist: tqdm
Requires-Dist: requests
Provides-Extra: docs
Requires-Dist: sphinx>=7.0.0; extra == "docs"
Requires-Dist: sphinx-rtd-theme>=2.0.0; extra == "docs"
Dynamic: home-page
Dynamic: requires-python
